{
  "SPDXID": "SPDXRef-DOCUMENT",
  "spdxVersion": "SPDX-2.3",
  "name": "SBOM-SPDX-tcl-tk-9.0.1",
  "creationInfo": {
    "created": "2025-01-04T01:05:49Z",
    "creators": [
      "Tool: https://github.com/Homebrew/brew@4.4.14-24-g20c6c5a"
    ]
  },
  "dataLicense": "CC0-1.0",
  "documentNamespace": "https://formulae.brew.sh/spdx/tcl-tk-9.0.1.json",
  "documentDescribes": [
    "SPDXRef-Archive-tcl-tk-src",
    "SPDXRef-Package-SPDXRef-ca-certificates-2024-12-31",
    "SPDXRef-Compiler"
  ],
  "files": [

  ],
  "packages": [
    {
      "SPDXID": "SPDXRef-Archive-tcl-tk-src",
      "name": "tcl-tk",
      "versionInfo": "9.0.1",
      "filesAnalyzed": false,
      "licenseDeclared": "NOASSERTION",
      "builtDate": "2024-12-19 18:00:59 UTC",
      "licenseConcluded": "TCL",
      "downloadLocation": "https://downloads.sourceforge.net/project/tcl/Tcl/9.0.1/tcl9.0.1-src.tar.gz",
      "copyrightText": "NOASSERTION",
      "externalRefs": [

      ],
      "checksums": [
        {
          "algorithm": "SHA256",
          "checksumValue": "a72b1607d7a399c75148c80fcdead88ed3371a29884181f200f2200cdee33bbc"
        }
      ]
    },
    {
      "SPDXID": "SPDXRef-Package-SPDXRef-ca-certificates-2024-12-31",
      "name": "ca-certificates",
      "versionInfo": "2024-12-31",
      "filesAnalyzed": false,
      "licenseDeclared": "NOASSERTION",
      "licenseConcluded": "MPL-2.0",
      "downloadLocation": "https://ghcr.io/v2/homebrew/core/ca-certificates/blobs/sha256:414ada64e60703cd4e9aa97f36e29c1a7ec73d60862b5219b8110731fcfd2cb7",
      "copyrightText": "NOASSERTION",
      "checksums": [
        {
          "algorithm": "SHA256",
          "checksumValue": "414ada64e60703cd4e9aa97f36e29c1a7ec73d60862b5219b8110731fcfd2cb7"
        }
      ],
      "externalRefs": [
        {
          "referenceCategory": "PACKAGE-MANAGER",
          "referenceLocator": "pkg:brew/ca-certificates@2024-12-31",
          "referenceType": "purl"
        }
      ]
    },
    {
      "SPDXID": "SPDXRef-Compiler",
      "name": "clang",
      "versionInfo": "16.2",
      "filesAnalyzed": false,
      "licenseDeclared": "NOASSERTION",
      "licenseConcluded": "NOASSERTION",
      "copyrightText": "NOASSERTION",
      "downloadLocation": "NOASSERTION",
      "checksums": [

      ],
      "externalRefs": [

      ]
    }
  ],
  "relationships": [
    {
      "spdxElementId": "SPDXRef-Package-SPDXRef-ca-certificates-2024-12-31",
      "relationshipType": "RUNTIME_DEPENDENCY_OF",
      "relatedSpdxElement": "SPDXRef-Bottle-tcl-tk"
    },
    {
      "spdxElementId": "SPDXRef-File-tcl-tk",
      "relationshipType": "PACKAGE_OF",
      "relatedSpdxElement": "SPDXRef-Archive-tcl-tk-src"
    },
    {
      "spdxElementId": "SPDXRef-Compiler",
      "relationshipType": "BUILD_TOOL_OF",
      "relatedSpdxElement": "SPDXRef-Package-tcl-tk-src"
    }
  ]
}